{
  "version": "1.0",
  "generated": "2026-03-11T19:13:22.245Z",
  "duration_ms": 721126,
  "total_jobs": 25501,
  "unique_jobs": 25501,
  "duplicates_removed": 17227,
  "by_source": {
    "workday": 16321,
    "ashby": 1458,
    "greenhouse": 5959,
    "lever": 1070,
    "jsearch": 10,
    "amazon": 584,
    "eightfold": 99
  },
  "by_employment_type": {
    "FULLTIME": 1285,
    "INTERN": 92,
    "FULL-TIME": 9,
    "FULL-TIME AND INTERNSHIP": 1,
    "CONTRACT": 72,
    "PARTTIME": 8,
    "TEMPORARY": 1
  },
  "by_job_type": {
    "internship": 2183,
    "new-grad": 21595,
    "mid_level": 1723
  },
  "by_location": {
    "remote": 1221,
    "onsite": 24280
  },
  "jsearch_stats": {
    "queries": [
      {
        "query": "machine learning engineer entry level",
        "count": 3
      },
      {
        "query": "entry level hardware engineer",
        "count": 5
      },
      {
        "query": "electrical engineer entry level new graduate",
        "count": 3
      }
    ],
    "total_fetched": 11
  },
  "ats_stats": {
    "companies_total": 286,
    "greenhouse_companies": 109,
    "lever_companies": 45,
    "ashby_companies": 62,
    "workday_tenants": 67,
    "eightfold_tenants": 3
  },
  "validation_stats": {
    "total_input": 56241,
    "valid_jobs": 56193,
    "invalid_jobs": 48,
    "invalid_reasons": {
      "missing_title": 20,
      "missing_company": 0,
      "missing_url": 0,
      "invalid_title_length": 28,
      "invalid_company_length": 0,
      "invalid_url_format": 0
    },
    "normalized_fields": {
      "state_extracted": 8726,
      "city_extracted": 17471
    }
  },
  "senior_filter_stats": {
    "total_input": 56193,
    "entry_level_jobs": 25501,
    "senior_jobs": 30692,
    "senior_reasons": {
      "senior_title": 17059,
      "senior_experience": 3178,
      "both": 10455
    },
    "by_source": {
      "greenhouse": 13605,
      "lever": 1507,
      "ashby": 3133,
      "workday": 11920,
      "eightfold": 101,
      "amazon": 426
    }
  },
  "tag_stats": {
    "employment": {
      "entry_level": 21595,
      "internship": 2183,
      "mid_level": 1723
    },
    "domains": {
      "ai": 432,
      "data_science": 1838,
      "software": 4671,
      "hardware": 1738,
      "general": 15499,
      "product": 118,
      "finance": 154,
      "nursing": 2719
    },
    "locations": {
      "us": 15571,
      "on_site": 812,
      "remote": 1221,
      "hybrid": 189
    },
    "experience": {
      "unknown": 18793,
      "entry_level": 3245,
      "mid_level": 2768,
      "senior_level": 695
    },
    "special": {
      "unicorn": 477,
      "faang": 574,
      "fortune500": 883
    },
    "total": 25501
  },
  "freshness": {
    "last_1h": 1423,
    "last_6h": 1626,
    "last_24h": 2182,
    "last_48h": 2937
  },
  "top_companies": [
    {
      "company": "SpaceX",
      "count": 1014
    },
    {
      "company": "Saint Luke's Health System",
      "count": 478
    },
    {
      "company": "Geisinger Health",
      "count": 473
    },
    {
      "company": "Ochsner Health",
      "count": 471
    },
    {
      "company": "WVU Medicine",
      "count": 466
    },
    {
      "company": "Cleveland Clinic",
      "count": 453
    },
    {
      "company": "Intermountain Health",
      "count": 444
    },
    {
      "company": "Mass General Brigham",
      "count": 442
    },
    {
      "company": "Morgan Stanley",
      "count": 441
    },
    {
      "company": "Banner Health",
      "count": 441
    },
    {
      "company": "Vanderbilt University Medical Center",
      "count": 439
    },
    {
      "company": "Nationwide Children's",
      "count": 434
    },
    {
      "company": "Anduril",
      "count": 392
    },
    {
      "company": "AT&T",
      "count": 370
    },
    {
      "company": "Applied Materials",
      "count": 366
    }
  ]
}