{
  "version": "1.0",
  "generated": "2026-03-11T16:19:14.244Z",
  "duration_ms": 688085,
  "total_jobs": 26640,
  "unique_jobs": 26640,
  "duplicates_removed": 18290,
  "by_source": {
    "workday": 16456,
    "ashby": 1459,
    "greenhouse": 6955,
    "lever": 1066,
    "jsearch": 7,
    "amazon": 583,
    "eightfold": 114
  },
  "by_employment_type": {
    "FULLTIME": 1286,
    "INTERN": 92,
    "FULL-TIME": 7,
    "CONTRACT": 72,
    "PARTTIME": 8,
    "TEMPORARY": 1
  },
  "by_job_type": {
    "internship": 2189,
    "new-grad": 22706,
    "mid_level": 1745
  },
  "by_location": {
    "remote": 1246,
    "onsite": 25394
  },
  "jsearch_stats": {
    "queries": [
      {
        "query": "entry level data scientist",
        "count": 5
      },
      {
        "query": "data analyst entry level",
        "count": 3
      },
      {
        "query": "machine learning engineer entry level",
        "count": 3
      }
    ],
    "total_fetched": 11
  },
  "ats_stats": {
    "companies_total": 287,
    "greenhouse_companies": 110,
    "lever_companies": 45,
    "ashby_companies": 62,
    "workday_tenants": 67,
    "eightfold_tenants": 3
  },
  "validation_stats": {
    "total_input": 58332,
    "valid_jobs": 58281,
    "invalid_jobs": 51,
    "invalid_reasons": {
      "missing_title": 23,
      "missing_company": 0,
      "missing_url": 0,
      "invalid_title_length": 28,
      "invalid_company_length": 0,
      "invalid_url_format": 0
    },
    "normalized_fields": {
      "state_extracted": 8698,
      "city_extracted": 17451
    }
  },
  "senior_filter_stats": {
    "total_input": 58281,
    "entry_level_jobs": 26640,
    "senior_jobs": 31641,
    "senior_reasons": {
      "senior_title": 18528,
      "senior_experience": 3119,
      "both": 9994
    },
    "by_source": {
      "jsearch": 1,
      "greenhouse": 14737,
      "lever": 1496,
      "ashby": 3143,
      "workday": 11753,
      "eightfold": 86,
      "amazon": 425
    }
  },
  "tag_stats": {
    "employment": {
      "entry_level": 22706,
      "mid_level": 1745,
      "internship": 2189
    },
    "domains": {
      "data_science": 1668,
      "software": 4809,
      "general": 16815,
      "ai": 432,
      "product": 118,
      "finance": 155,
      "hardware": 1201,
      "nursing": 2700
    },
    "locations": {
      "us": 16306,
      "on_site": 811,
      "remote": 1246,
      "hybrid": 190
    },
    "experience": {
      "unknown": 20054,
      "mid_level": 2719,
      "senior_level": 674,
      "entry_level": 3193
    },
    "special": {
      "unicorn": 482,
      "faang": 603,
      "fortune500": 880
    },
    "total": 26640
  },
  "freshness": {
    "last_1h": 970,
    "last_6h": 1066,
    "last_24h": 1819,
    "last_48h": 3008
  },
  "top_companies": [
    {
      "company": "SpaceX",
      "count": 1014
    },
    {
      "company": "Speechify",
      "count": 991
    },
    {
      "company": "Saint Luke's Health System",
      "count": 477
    },
    {
      "company": "Geisinger Health",
      "count": 473
    },
    {
      "company": "Ochsner Health",
      "count": 469
    },
    {
      "company": "WVU Medicine",
      "count": 464
    },
    {
      "company": "Cleveland Clinic",
      "count": 458
    },
    {
      "company": "Mass General Brigham",
      "count": 441
    },
    {
      "company": "Intermountain Health",
      "count": 441
    },
    {
      "company": "Morgan Stanley",
      "count": 439
    },
    {
      "company": "Vanderbilt University Medical Center",
      "count": 439
    },
    {
      "company": "Banner Health",
      "count": 438
    },
    {
      "company": "Nationwide Children's",
      "count": 434
    },
    {
      "company": "Anduril",
      "count": 388
    },
    {
      "company": "AT&T",
      "count": 367
    }
  ]
}