{"id":"js-t-mobile-_kykk7cbb3ljyjw3aaaaaa==","fingerprint":"3d13caac77b885fc159f8d580c20dd5509d1074dfefc62377a6f9f8e95d50ea9","title":"Sr Engineer, Software","company":"T-Mobile","company_slug":"t-mobile","location":"Frisco, Texas","remote":false,"url":"https://www.ziprecruiter.com/c/T-Mobile/Job/Sr.-Engineer,-Software/-in-Frisco,TX?jid=48a4e53761471fda&utm_campaign=google_jobs_apply&utm_source=google_jobs_apply&utm_medium=organic","posted_at":"2026-01-08T00:00:00.000Z","source":"jsearch","employment_types":["FULL-TIME"],"experience_level":"entry","description":"At T-Mobile, we invest in YOU! Our Total Rewards Package ensures that employees get the same big love we give our customers. All team members receive a competitive base salary and compensation package - this is Total Rewards. Employees enjoy multiple wealth-building opportunities through our annual stock grant, employee stock purchase plan, 401(k), and access to free, year-round money coaches. That's how we're UNSTOPPABLE for our employees!\n\nJob Overview\nThe Sr Software Engineer works with a team of other software engineers, network and systems engineers to design, implement, and deploy software which meet customer's requirements, scales easily, removes the limitations of traditional networking solutions, and supports deployment in highly available environments. The Sr Software Engineer actively participates in architecture and design of various software components focused on creating applications that leverage technologies such as virtualization, micro services, SDN, NFV, and Big Data platforms and technologies. They work on technical assignments that are moderately difficult, requiring judgment in resolving issues or in making recommendations. They work on assignments requiring considerable judgment and initiative, understand implications of work and make recommendations for solutions. They normally receive little instruction on daily work, and only require general instructions on newly introduced assignments.\n\nJob Responsibilities:\n• Technical Engineering Services\n- Drives engineering projects by developing software solutions; conducting tests and inspections; preparing reports and calculations. Expected to supervise base and associate level engineers as needed.\n- Understands system protocols, how systems operate and data flows. Aware of current technology benefits. Expected to independently develop a full software stack. Understands the building blocks, interactions, dependencies, and tools required to complete software and automation work. Independent study of current technology is expected. Interact with system engineers to define system requirement and/or necessary requirements for automation.\n• Innovation\n- Contributes to designs to implement new ideas which utilize new frameworks to improve an existing or new system/process/service.\n- Review existing designs and processes to highlight more efficient ways to complete existing workload more effectively through industry perspectives.\n- Understands the creation of company IPR.\n• Technical Leadership\n- Collaborates with technical teams and utilizes system expertise to deliver technical solutions.\n- Continuously learns and teaches others existing and new technologies.\n- Contributes to the development of others through mentoring or in house workshops and learning sessions.\n• Technology Strategy\n- Contributes to new and existing technology options that support business goals.\n- Understands current technology that supports business goals. Understands system protocols, how systems operate and data flows. Aware of current technology benefits. Expected to independently develop a full software stack. Understands the building blocks, interactions, dependencies, and tools required to complete software and automation work. Independent study of current technology is expected. Interact with system engineers to define system requirement and/or necessary requirements for automation.\n• Technical Writing\n- Writes basic documentation on how technology works. Creates clear documentation for new code and systems used.\n- Documenting systems designs, presentations, and business requirements for consumption and consideration at the manager level.\n\nEducation and Work Experience:\n• Bachelor's Degree Computer Science or Engineering (Required)\n• 4-7 years - Technical engineering experience.\n\nTechnical Skills:\n• Programming Languages: Java (17 & 21), JavaScript, TypeScript, SQL, PL/SQL, Gherkin, Shell Scripting, NodeJS\n• Framework: MVC, Spring Boot, Struts, EJB, Spring Cloud, Servlets, OAuth2, JPA, Hibernate\n• Frontend: Angular, React, JSP, HTML5, CSS3, Bootstrap, Material UI\n• Backend: Spring Boot, RESTful APIs, Microservices, SOAP Services, Swagger, WSDL\n• Cloud Platforms: Amazon Web Services (AWS)\n• DevOps Tools: Jenkins, Git, Maven, Docker, Kubernetes, Gitlab, Gitlab CI/CD\n• Databases: Oracle\n• Methodologies: Agile (Scrum/Kanban), CI/CD Automation\n• Testing Tools: Karate, Bruno, Postman, SOAP UI, Cucumber, Rest Assured\n• Monitoring: Grafana, Splunk, AppDynamics\n• Tools: IntelliJ, VS Code, SQL Developer, TOAD\n\nKnowledge, Skills and Abilities:\n• Communication (Required)\n• Customer Service (Required)\n• Analytics (Required)\n• Technical Writing (Required)\n\nLicenses and Certifications:\n• At least 18 years of age\n• Legally authorized to work in the United States\n\nTravel:\nTravel Required (Yes/No): Yes\n\nDOT Regulated:\nDOT Regulated Position (Yes/No): No\nSafety Sensitive Position (Yes/No): No\n\nBase Pay Range: $113,600 - $205,000\n\nCorporate Bonus Target: 15%\n\nThe pay range above is the general base pay range for a successful candidate in the role. The successful candidate's actual pay will be based on various factors, such as work location, qualifications, and experience, so the actual starting pay will vary within this range.\n\nAt T-Mobile, employees in regular, non-temporary roles are eligible for an annual bonus or periodic sales incentive or bonus, based on their role. Most Corporate employees are eligible for a year-end bonus based on company and/or individual performance and which is set at a percentage of the employee's eligible earnings in the prior year. Certain positions in Customer Care are eligible for monthly bonuses based on individual and/or team performance. To find the pay range for this role based on hiring location, https://paylookup.t-mobile.com/paylookup?reqID=REQ338353¶dox=1\n\nAt T-Mobile, our benefits exemplify the spirit of One Team, Together! A big part of how we care for one another is working to ensure our benefits evolve to meet the needs of our team members. Full and part-time employees have access to the same benefits when eligible. We cover all of the bases, offering medical, dental and vision insurance, a flexible spending account, 401(k), employee stock grants, employee stock purchase plan, paid time off and up to 12 paid holidays - which total about 4 weeks for new full-time employees and about 2.5 weeks for new part-time employees annually - paid parental and family leave, family building benefits, back-up care, enhanced family support, childcare subsidy, tuition assistance, college coaching, short- and long-term disability, voluntary AD&D coverage, voluntary accident coverage, voluntary life insurance, voluntary disability insurance, and voluntary long-term care insurance. We don't stop there - eligible employees can also receive mobile service & home internet discounts, pet insurance, and access to commuter and transit programs! To learn about T-Mobile's amazing benefits, check out www.t-mobilebenefits.com.\n\nNever stop growing!\nAs part of the T-Mobile team, you know the Un-carrier doesn't have a corporate ladder-it's more like a jungle gym of possibilities! We love helping our employees grow in their careers, because it's that shared drive to aim high that drives our business and our culture forward. By applying for this career opportunity, you're living our values while investing in your career growth-and we applaud it. You're unstoppable!\n\nT-Mobile USA, Inc. is an Equal Opportunity Employer. All decisions concerning the employment relationship will be made without regard to age, race, ethnicity, color, religion, creed, sex, sexual orientation, gender identity or expression, national origin, religious affiliation, marital status, citizenship status, veteran status, the presence of any physical or mental disability, or any other status or characteristic protected by federal, state, or local law. Discrimination, retaliation or harassment based upon any of these factors is wholly inconsistent with how we do business and will not be tolerated.\n\nTalent comes in all forms at the Un-carrier. If you are an individual with a disability and need reasonable accommodation at any point in the application or interview process, please let us know by emailing ApplicantAccommodation@t-mobile.com or calling 1-844-873-9500. Please note, this contact channel is not a means to apply for or inquire about a position and we are unable to respond to non-accommodation related requests.","enriched":false,"enriched_at":null,"is_internship":false,"is_new_grad":false,"is_remote":false,"is_us_only":true,"_raw":{"job_id":"_KYkK7cBB3ljyjw3AAAAAA==","job_publisher":"ZipRecruiter","job_latitude":33.1496718,"job_longitude":-96.835567},"tags":{"employment":"senior","domains":["general"],"locations":["us","on_site"],"experience":"no_experience","special":[]}}
