{
  "version": "1.0",
  "generated": "2026-03-14T18:18:22.983Z",
  "duration_ms": 760455,
  "total_jobs": 32731,
  "unique_jobs": 32731,
  "duplicates_removed": 21255,
  "by_source": {
    "workday": 20755,
    "lever": 1005,
    "greenhouse": 6992,
    "jsearch": 16,
    "smartrecruiters": 1867,
    "ashby": 1422,
    "amazon": 494,
    "netflix": 99,
    "eightfold": 81
  },
  "by_employment_type": {
    "FULL-TIME": 1573,
    "INTERNSHIP": 4,
    "FULL-TIME AND PART-TIME": 1,
    "FULLTIME": 1243,
    "CONTRACT": 83,
    "INTERN": 91,
    "FULL-TIME AND INTERNSHIP": 2,
    "PARTTIME": 8,
    "TEMPORARY": 1
  },
  "by_job_type": {
    "internship": 2954,
    "new-grad": 29317,
    "mid_level": 460
  },
  "by_location": {
    "remote": 1744,
    "onsite": 30987
  },
  "jsearch_stats": {
    "queries": [
      {
        "query": "hardware engineer intern",
        "count": 5
      },
      {
        "query": "electrical engineering internship",
        "count": 10
      },
      {
        "query": "embedded systems engineer entry level",
        "count": 2
      }
    ],
    "total_fetched": 17
  },
  "ats_stats": {
    "companies_total": 382,
    "greenhouse_companies": 145,
    "lever_companies": 45,
    "ashby_companies": 62,
    "workday_tenants": 110,
    "eightfold_tenants": 3,
    "smartrecruiters_companies": 17
  },
  "validation_stats": {
    "total_input": 74984,
    "valid_jobs": 74947,
    "invalid_jobs": 37,
    "invalid_reasons": {
      "missing_title": 4,
      "missing_company": 0,
      "missing_url": 0,
      "invalid_title_length": 33,
      "invalid_company_length": 0,
      "invalid_url_format": 0
    },
    "normalized_fields": {
      "state_extracted": 13574,
      "city_extracted": 24960
    }
  },
  "senior_filter_stats": {
    "total_input": 74947,
    "entry_level_jobs": 32731,
    "senior_jobs": 42216,
    "senior_reasons": {
      "senior_title": 26402,
      "senior_experience": 3593,
      "both": 12221
    },
    "by_source": {
      "jsearch": 1,
      "greenhouse": 16588,
      "lever": 1570,
      "ashby": 3173,
      "workday": 17525,
      "eightfold": 112,
      "smartrecruiters": 2589,
      "amazon": 517,
      "netflix": 141
    }
  },
  "tag_stats": {
    "employment": {
      "internship": 2954,
      "entry_level": 29317,
      "mid_level": 460
    },
    "domains": {
      "hardware": 3015,
      "software": 6031,
      "data_science": 2380,
      "general": 17014,
      "sales": 2226,
      "ai": 560,
      "legal": 129,
      "operations": 390,
      "product": 213,
      "finance": 161,
      "hr": 127,
      "marketing": 157,
      "healthcare": 2912
    },
    "locations": {
      "us": 19570,
      "on_site": 2300,
      "remote": 1744,
      "hybrid": 178
    },
    "experience": {
      "entry_level": 4135,
      "unknown": 24915,
      "mid_level": 2971,
      "senior_level": 710
    },
    "special": {
      "unicorn": 471,
      "faang": 594,
      "fortune500": 816
    },
    "total": 32731
  },
  "freshness": {
    "last_1h": 52,
    "last_6h": 69,
    "last_24h": 486,
    "last_48h": 1758
  },
  "top_companies": [
    {
      "company": "SpaceX",
      "count": 1018
    },
    {
      "company": "Morgan Stanley",
      "count": 469
    },
    {
      "company": "Saint Luke's Health System",
      "count": 468
    },
    {
      "company": "Ochsner Health",
      "count": 463
    },
    {
      "company": "Geisinger Health",
      "count": 462
    },
    {
      "company": "WVU Medicine",
      "count": 459
    },
    {
      "company": "Intermountain Health",
      "count": 449
    },
    {
      "company": "Banner Health",
      "count": 436
    },
    {
      "company": "Vanderbilt University Medical Center",
      "count": 434
    },
    {
      "company": "Cleveland Clinic",
      "count": 425
    },
    {
      "company": "Nationwide Children's",
      "count": 408
    },
    {
      "company": "T-Mobile",
      "count": 404
    },
    {
      "company": "Anduril",
      "count": 387
    },
    {
      "company": "AT&T",
      "count": 381
    },
    {
      "company": "Mass General Brigham",
      "count": 373
    }
  ]
}