{
  "version": "1.0",
  "generated": "2026-03-13T18:52:07.943Z",
  "duration_ms": 741594,
  "total_jobs": 30728,
  "unique_jobs": 30728,
  "duplicates_removed": 21031,
  "by_source": {
    "workday": 19113,
    "smartrecruiters": 1973,
    "greenhouse": 6433,
    "lever": 1070,
    "ashby": 1435,
    "amazon": 599,
    "jsearch": 20,
    "eightfold": 85
  },
  "by_employment_type": {
    "FULL-TIME": 1672,
    "FULLTIME": 1265,
    "INTERNSHIP": 6,
    "INTERN": 90,
    "CONTRACT": 75,
    "FULL-TIME AND INTERNSHIP": 2,
    "PART-TIME": 2,
    "PARTTIME": 8,
    "TEMPORARY": 1
  },
  "by_job_type": {
    "internship": 2864,
    "new-grad": 25962,
    "mid_level": 1902
  },
  "by_location": {
    "remote": 1646,
    "onsite": 29082
  },
  "jsearch_stats": {
    "queries": [
      {
        "query": "systems engineering internship",
        "count": 8
      },
      {
        "query": "finance internship technology",
        "count": 6
      },
      {
        "query": "software engineer intern",
        "count": 6
      }
    ],
    "total_fetched": 20
  },
  "ats_stats": {
    "companies_total": 332,
    "greenhouse_companies": 126,
    "lever_companies": 45,
    "ashby_companies": 62,
    "workday_tenants": 79,
    "eightfold_tenants": 3,
    "smartrecruiters_companies": 17
  },
  "validation_stats": {
    "total_input": 67375,
    "valid_jobs": 67334,
    "invalid_jobs": 41,
    "invalid_reasons": {
      "missing_title": 17,
      "missing_company": 0,
      "missing_url": 0,
      "invalid_title_length": 24,
      "invalid_company_length": 0,
      "invalid_url_format": 0
    },
    "normalized_fields": {
      "state_extracted": 12994,
      "city_extracted": 23056
    }
  },
  "senior_filter_stats": {
    "total_input": 67334,
    "entry_level_jobs": 30728,
    "senior_jobs": 36606,
    "senior_reasons": {
      "senior_title": 22261,
      "senior_experience": 3343,
      "both": 11002
    },
    "by_source": {
      "greenhouse": 14645,
      "lever": 1502,
      "ashby": 3148,
      "workday": 14287,
      "eightfold": 118,
      "smartrecruiters": 2484,
      "amazon": 422
    }
  },
  "tag_stats": {
    "employment": {
      "internship": 2864,
      "entry_level": 25962,
      "mid_level": 1902
    },
    "domains": {
      "software": 6050,
      "hardware": 3306,
      "general": 15047,
      "data_science": 2256,
      "sales": 1931,
      "ai": 540,
      "legal": 116,
      "operations": 376,
      "product": 193,
      "finance": 153,
      "hr": 118,
      "marketing": 143,
      "healthcare": 3010
    },
    "locations": {
      "us": 18762,
      "on_site": 2413,
      "remote": 1646,
      "hybrid": 185
    },
    "experience": {
      "entry_level": 3947,
      "mid_level": 2890,
      "unknown": 23170,
      "senior_level": 721
    },
    "special": {
      "unicorn": 482,
      "faang": 585,
      "fortune500": 899
    },
    "total": 30728
  },
  "freshness": {
    "last_1h": 1297,
    "last_6h": 1638,
    "last_24h": 2502,
    "last_48h": 3252
  },
  "top_companies": [
    {
      "company": "SpaceX",
      "count": 1022
    },
    {
      "company": "Stryker",
      "count": 666
    },
    {
      "company": "ASML",
      "count": 594
    },
    {
      "company": "HP Inc",
      "count": 554
    },
    {
      "company": "Cisco",
      "count": 543
    },
    {
      "company": "Broadcom",
      "count": 520
    },
    {
      "company": "Disney",
      "count": 480
    },
    {
      "company": "Saint Luke's Health System",
      "count": 477
    },
    {
      "company": "Geisinger Health",
      "count": 474
    },
    {
      "company": "Morgan Stanley",
      "count": 467
    },
    {
      "company": "WVU Medicine",
      "count": 466
    },
    {
      "company": "Ochsner Health",
      "count": 465
    },
    {
      "company": "Cleveland Clinic",
      "count": 454
    },
    {
      "company": "Intermountain Health",
      "count": 452
    },
    {
      "company": "Mass General Brigham",
      "count": 451
    }
  ]
}