{
  "version": "1.0",
  "generated": "2026-02-23T17:12:12.255Z",
  "duration_ms": 79110,
  "total_jobs": 2250,
  "unique_jobs": 2250,
  "duplicates_removed": 1850,
  "by_source": {
    "greenhouse": 1805,
    "ashby": 324,
    "lever": 121
  },
  "by_employment_type": {
    "FULLTIME": 316,
    "CONTRACT": 1,
    "TEMPORARY": 1,
    "INTERN": 6
  },
  "by_job_type": {
    "internship": 0,
    "new-grad": 0,
    "other": 2250
  },
  "by_location": {
    "remote": 102,
    "onsite": 2148
  },
  "jsearch_stats": {
    "date": "2026-02-23",
    "requests_today": 1,
    "remaining_today": 299,
    "total_jobs_fetched": 119,
    "avg_jobs_per_request": "119.0"
  },
  "ats_stats": {
    "companies_total": 37,
    "greenhouse_companies": 30,
    "lever_companies": 2,
    "ashby_companies": 5
  },
  "validation_stats": {
    "total_input": 8778,
    "valid_jobs": 8659,
    "invalid_jobs": 119,
    "invalid_reasons": {
      "missing_title": 0,
      "missing_company": 119,
      "missing_url": 0,
      "invalid_title_length": 0,
      "invalid_company_length": 0,
      "invalid_url_format": 0
    },
    "normalized_fields": {
      "state_extracted": 1213,
      "city_extracted": 1827
    }
  },
  "senior_filter_stats": {
    "total_input": 8659,
    "entry_level_jobs": 2250,
    "senior_jobs": 6409,
    "senior_reasons": {
      "senior_title": 1745,
      "senior_experience": 1173,
      "both": 3491
    }
  },
  "tag_stats": {
    "employment": {
      "entry_level": 1957,
      "mid_level": 117,
      "internship": 176
    },
    "domains": {
      "general": 973,
      "software": 878,
      "data_science": 381,
      "product": 227,
      "hardware": 22
    },
    "locations": {
      "us": 965,
      "remote": 255,
      "on_site": 221
    },
    "experience": {
      "3_plus_years": 1756,
      "under_3_years": 107,
      "no_experience": 387
    },
    "special": {},
    "total": 2250
  }
}